treasurecx/__init__.py
treasurecx/asynchronous.py
treasurecx-1.0.1.dist-info/LICENSE
treasurecx-1.0.1.dist-info/METADATA
treasurecx-1.0.1.dist-info/WHEEL
treasurecx-1.0.1.dist-info/top_level.txt
treasurecx-1.0.1.dist-info/RECORD
