Metadata-Version: 2.1
Name: treasurecx
Version: 1.0.1
Summary: Advanced Python wrapper for "treasure.cx".
Home-page: https://github.com/TriDiscord/treasurecx
Author: Tri
Author-email: tricdiscord@gmail.com
License: UNKNOWN
Project-URL: Bug Tracker, https://github.com/TriDiscord/treasurecx/issues
Platform: UNKNOWN
Classifier: Programming Language :: Python :: 3
Classifier: License :: OSI Approved :: MIT License
Classifier: Operating System :: OS Independent
Requires-Python: >=3.6
License-File: LICENSE
Requires-Dist: aiohttp (>=4.0.0a1)
